{
	"cmake" : 
	{
		"generator" : 
		{
			"name" : "Ninja"
		},
		"paths" : 
		{
			"cmake" : "/home/saurav/anaconda3/envs/ros_env/bin/cmake",
			"cpack" : "/home/saurav/anaconda3/envs/ros_env/bin/cpack",
			"ctest" : "/home/saurav/anaconda3/envs/ros_env/bin/ctest",
			"root" : "/home/saurav/anaconda3/envs/ros_env/share/cmake-3.14"
		},
		"version" : 
		{
			"isDirty" : false,
			"major" : 3,
			"minor" : 14,
			"patch" : 0,
			"string" : "3.14.0",
			"suffix" : ""
		}
	},
	"objects" : 
	[
		{
			"jsonFile" : "codemodel-v2-1a9b192ce25f4379d350.json",
			"kind" : "codemodel",
			"version" : 
			{
				"major" : 2,
				"minor" : 0
			}
		},
		{
			"jsonFile" : "cache-v2-ae16442d688a78bdde68.json",
			"kind" : "cache",
			"version" : 
			{
				"major" : 2,
				"minor" : 0
			}
		},
		{
			"jsonFile" : "cmakeFiles-v1-c4f8b4aff9fedc560daf.json",
			"kind" : "cmakeFiles",
			"version" : 
			{
				"major" : 1,
				"minor" : 0
			}
		}
	],
	"reply" : 
	{
		"client-integration-vscode" : 
		{
			"cache-v2" : 
			{
				"jsonFile" : "cache-v2-ae16442d688a78bdde68.json",
				"kind" : "cache",
				"version" : 
				{
					"major" : 2,
					"minor" : 0
				}
			},
			"cmakeFiles-v1" : 
			{
				"jsonFile" : "cmakeFiles-v1-c4f8b4aff9fedc560daf.json",
				"kind" : "cmakeFiles",
				"version" : 
				{
					"major" : 1,
					"minor" : 0
				}
			},
			"codemodel-v2" : 
			{
				"jsonFile" : "codemodel-v2-1a9b192ce25f4379d350.json",
				"kind" : "codemodel",
				"version" : 
				{
					"major" : 2,
					"minor" : 0
				}
			}
		},
		"client-vscode-cmake-lite" : 
		{
			"query.json" : 
			{
				"requests" : 
				[
					{
						"kind" : "codemodel",
						"version" : 
						[
							{
								"major" : 2
							}
						]
					},
					{
						"kind" : "cache",
						"version" : 
						[
							{
								"major" : 2
							}
						]
					},
					{
						"kind" : "cmakeFiles",
						"version" : 
						[
							{
								"major" : 1
							}
						]
					}
				],
				"responses" : 
				[
					{
						"jsonFile" : "codemodel-v2-1a9b192ce25f4379d350.json",
						"kind" : "codemodel",
						"version" : 
						{
							"major" : 2,
							"minor" : 0
						}
					},
					{
						"jsonFile" : "cache-v2-ae16442d688a78bdde68.json",
						"kind" : "cache",
						"version" : 
						{
							"major" : 2,
							"minor" : 0
						}
					},
					{
						"jsonFile" : "cmakeFiles-v1-c4f8b4aff9fedc560daf.json",
						"kind" : "cmakeFiles",
						"version" : 
						{
							"major" : 1,
							"minor" : 0
						}
					}
				]
			}
		}
	}
}
